archive_and_release-1.0.2.dist-info/licenses/LICENSE
releaser/__init__.py
releaser/constants.py
releaser/release.py
releaser/errors/__init__.py
releaser/errors/errors.py
releaser/utilities/__init__.py
releaser/utilities/errors_util.py
releaser/utilities/file_util.py
releaser/utilities/git_util.py
releaser/utilities/github_util.py
releaser/utilities/helpers.py
releaser/utilities/log_util.py
releaser/utilities/time_util.py
releaser/utilities/zip_util.py
archive_and_release-1.0.2.dist-info/METADATA
archive_and_release-1.0.2.dist-info/WHEEL
archive_and_release-1.0.2.dist-info/entry_points.txt
archive_and_release-1.0.2.dist-info/top_level.txt
archive_and_release-1.0.2.dist-info/RECORD
