Metadata-Version: 2.4
Name: archive-and-release
Version: 1.0.2
Summary: "A cli archiving bunch of files (e.g. bash scripts), from a git repository made up of a number of (public/private) sub modules, and optionally tagging it and creating a github release for it with the resulting archive."
Home-page: https://github.com/dan-east/cloud-release-builder
Author: Dan East
Requires-Python: >=3.10
License-File: LICENSE
Requires-Dist: GitPython
Requires-Dist: PyGithub
Requires-Dist: python-dotenv
Provides-Extra: test
Requires-Dist: pytest; extra == "test"
Dynamic: license-file
